pytsmod/__init__.py
pytsmod/console/__init__.py
pytsmod/console/console.py
pytsmod/console/descs.conf
pytsmod/hptsm.py
pytsmod/olatsm.py
pytsmod/pvtsm.py
pytsmod/solatsm.py
pytsmod/tdpsolatsm.py
pytsmod/utils/__init__.py
pytsmod/utils/stft.py
pytsmod/utils/validate.py
pytsmod/utils/win.py
pytsmod/wsolatsm.py
pytsmod-0.3.8.dist-info/LICENSE
pytsmod-0.3.8.dist-info/METADATA
pytsmod-0.3.8.dist-info/WHEEL
pytsmod-0.3.8.dist-info/entry_points.txt
pytsmod-0.3.8.dist-info/RECORD
