Metadata-Version: 2.1
Name: pytsmod
Version: 0.3.8
Summary: An open-source Python library for audio time-scale modification.
License: GPL-3.0
Author: Sangeon Yong
Author-email: koragon2@kaist.ac.kr
Requires-Python: >=3.9,<3.13
Classifier: License :: OSI Approved :: GNU General Public License v3 (GPLv3)
Classifier: Programming Language :: Python :: 3
Classifier: Programming Language :: Python :: 3.9
Classifier: Programming Language :: Python :: 3.10
Classifier: Programming Language :: Python :: 3.11
Classifier: Programming Language :: Python :: 3.12
Requires-Dist: numpy (>=1.20)
Requires-Dist: scipy (>=1.8)
Requires-Dist: soundfile (>=0.10)
